matreex/__init__.py
matreex/_runners.py
matreex/matreex.py
matreex/run_matreex.py
matreex-0.1.2.data/scripts/matreex
matreex-0.1.2.dist-info/METADATA
matreex-0.1.2.dist-info/WHEEL
matreex-0.1.2.dist-info/top_level.txt
matreex-0.1.2.dist-info/RECORD
