Metadata-Version: 2.1
Name: matreex
Version: 0.1.2
Summary: Matreex: compact and interactive visualisation of large gene families using hierarchical phylogenetic profiles
Home-page: https://github.com/DessimozLab/matreex
Author: Victor Rossier and Clement Train
License: LGPLv3
Platform: UNKNOWN
Requires-Python: >=3.6
Requires-Dist: biopython
Requires-Dist: ete3
Requires-Dist: omadb
Requires-Dist: requests
Requires-Dist: pyham
